publish_deno.py
publish_deno-1.0.1.dist-info/entry_points.txt
publish_deno-1.0.1.dist-info/WHEEL
publish_deno-1.0.1.dist-info/METADATA
publish_deno-1.0.1.dist-info/RECORD
