Metadata-Version: 2.1
Name: publish-deno
Version: 1.0.1
Summary: a script to update a Deno package
License: GPL-3.0
Author: Zamiell
Author-email: 5511220+Zamiell@users.noreply.github.com
Requires-Python: >=3.9,<4.0
Classifier: License :: OSI Approved :: GNU General Public License v3 (GPLv3)
Classifier: Programming Language :: Python :: 3
Classifier: Programming Language :: Python :: 3.9
